zqpy/__init__.py
zqpy/__version__.py
zqpy/zq_adb.py
zqpy/zq_const.py
zqpy/zq_email.py
zqpy/zq_excel.py
zqpy/zq_file.py
zqpy/zq_ftp.py
zqpy/zq_git.py
zqpy/zq_http.py
zqpy/zq_log.py
zqpy/zq_selenium.py
zqpy/zq_svn.py
zqpy/zq_time.py
zqpy/zq_watchdog.py
zqpy/zq_web.py
zqpy/zq_work_wx.py
zqpy/zq_ws.py
zqpy/zq_cv/__init__.py
zqpy/zq_cv/zq_cv.py
zqpy/zq_cv/zq_cv_img.py
zqpy/zq_cv/zq_cv_text.py
zqpy/zq_cv/zq_cv_video.py
zqpy/zq_db/__init__.py
zqpy/zq_db/zq_mongodb.py
zqpy/zq_db/zq_sqlite.py
zqpy/zq_tools/__init__.py
zqpy/zq_tts/__init__.py
zqpy/zq_tts/zq_tts_pyttsx3.py
zqpy/zq_tts/zq_tts_tencent.py
zqpy/zq_tts/zq_tts_win32com.py
zqpy/zq_tts/zq_tts_youdao.py
zqpy-1.1.6.dist-info/METADATA
zqpy-1.1.6.dist-info/WHEEL
zqpy-1.1.6.dist-info/top_level.txt
zqpy-1.1.6.dist-info/RECORD
